pythongraphrunner/TaskGraph.py
pythongraphrunner/__init__.py
pythongraphrunner-1.2.1.dist-info/LICENSE
pythongraphrunner-1.2.1.dist-info/METADATA
pythongraphrunner-1.2.1.dist-info/WHEEL
pythongraphrunner-1.2.1.dist-info/RECORD
