Metadata-Version: 2.1
Name: pythongraphrunner
Version: 1.2.1
Summary: A micro-library that makes it easy to write code that runs as part of a state machine.
License: MIT
Author: Adithya Yerramsetty
Author-email: adithyay@hotmail.com
Requires-Python: >=3.10,<4.0
Classifier: License :: OSI Approved :: MIT License
Classifier: Programming Language :: Python :: 3
Classifier: Programming Language :: Python :: 3.10
Classifier: Programming Language :: Python :: 3.11
Requires-Dist: networkx (>=3.1,<4.0)
